zfunc/__init__.py
zfunc/zfunc.py
zfunc-0.1.dist-info/METADATA
zfunc-0.1.dist-info/WHEEL
zfunc-0.1.dist-info/top_level.txt
zfunc-0.1.dist-info/RECORD
