Metadata-Version: 2.1
Name: zfunc
Version: 0.1
Summary: 这是一个自定义函数Python 库
Home-page: https://github.com/sos528/zfunc
Author: sos528
Author-email: 363854613@qq.com
Classifier: Programming Language :: Python :: 3
Classifier: License :: OSI Approved :: MIT License
Classifier: Operating System :: OS Independent
Requires-Python: >=3.8
